treefy/__init__.py
treefy/tree.py
treefy-0.1.dist-info/LICENSE
treefy-0.1.dist-info/METADATA
treefy-0.1.dist-info/WHEEL
treefy-0.1.dist-info/top_level.txt
treefy-0.1.dist-info/RECORD
