Metadata-Version: 2.1
Name: treefy
Version: 0.1
Summary: A dynamic tree library for algorithmic problem solving
Home-page: https://github.com/devenkapadia/treefy.git
Author: Deven Kapadia
Author-email: devenkapadia1@gmail.com
Classifier: Programming Language :: Python :: 3
Classifier: License :: OSI Approved :: MIT License
Classifier: Operating System :: OS Independent
Requires-Python: >=3.6
License-File: LICENSE
